alchemy1115/__init__.py
alchemy1115/profile.py
alchemy1115-1.0.0.dist-info/METADATA
alchemy1115-1.0.0.dist-info/WHEEL
alchemy1115-1.0.0.dist-info/entry_points.txt
alchemy1115-1.0.0.dist-info/licenses/LICENSE
alchemy1115-1.0.0.dist-info/RECORD
