Metadata-Version: 2.4
Name: alchemy1115
Version: 1.0.0
Summary: Profile display command line tool
Project-URL: Homepage, https://github.com/alchemy-1115/profile_card
Project-URL: Issues, https://github.com/alchemy-1115/profile_card/issues
Author: alchemy-1115
License: MIT
License-File: LICENSE
Keywords: alchemy-1115,profile
Classifier: Development Status :: 4 - Beta
Classifier: Intended Audience :: Developers
Classifier: License :: OSI Approved :: MIT License
Classifier: Programming Language :: Python :: 3
Classifier: Programming Language :: Python :: 3.9
Classifier: Programming Language :: Python :: 3.10
Classifier: Programming Language :: Python :: 3.11
Classifier: Programming Language :: Python :: 3.12
Classifier: Programming Language :: Python :: 3.13
Classifier: Topic :: Terminals
Classifier: Topic :: Utilities
Requires-Python: >=3.9
Requires-Dist: rich>=13.0.0
Requires-Dist: typer>=0.9.0
